g_python/__init__.py
g_python/g_python_bot.py
g_python/gextension.py
g_python/hdirection.py
g_python/hmessage.py
g_python/hpacket.py
g_python/hparsers.py
g_python/htools.py
g_python/hunityparsers.py
g_python/hunitytools.py
g_python-0.1.6.dist-info/LICENSE
g_python-0.1.6.dist-info/METADATA
g_python-0.1.6.dist-info/WHEEL
g_python-0.1.6.dist-info/top_level.txt
g_python-0.1.6.dist-info/RECORD
